MANIFEST.in
README.md
setup.py
tmiddleware-console.jpg
tmiddleware-web.jpg
TMiddleware.egg-info/PKG-INFO
TMiddleware.egg-info/SOURCES.txt
TMiddleware.egg-info/dependency_links.txt
TMiddleware.egg-info/not-zip-safe
TMiddleware.egg-info/requires.txt
TMiddleware.egg-info/top_level.txt
tests/__init__.py
tests/test_demo.py
tmiddleware/__init__.py
tmiddleware/handler.py
tmiddleware/plugins/__init__.py
tmiddleware/plugins/backend.py
tmiddleware/plugins/profile.py
tmiddleware/plugins/session.py
tmiddleware/plugins/slow_request.py