Metadata-Version: 1.0
Name: TMiddleware
Version: 0.0.1
Summary: tornado middleware
Home-page: https://github.com/iamsk/tmiddleware
Author: iamsk
Author-email: iamsk.info@gmail.com
License: UNKNOWN
Platform: UNKNOWN
Classifier: Development Status :: 3 - Alpha
Classifier: Environment :: Web Environment
Classifier: Intended Audience :: Developers
Classifier: License :: OSI Approved :: MIT License
Classifier: Operating System :: OS Independent
Classifier: Programming Language :: Python
Classifier: Programming Language :: Python :: 2.6
Classifier: Programming Language :: Python :: 2.7
